multiprocessed_socket/__init__.py
multiprocessed_socket/multiprocessed_socket.py
multiprocessed_socket-0.1.5.dist-info/LICENSE.txt
multiprocessed_socket-0.1.5.dist-info/METADATA
multiprocessed_socket-0.1.5.dist-info/WHEEL
multiprocessed_socket-0.1.5.dist-info/top_level.txt
multiprocessed_socket-0.1.5.dist-info/RECORD
