Metadata-Version: 2.1
Name: multiprocessed_socket
Version: 0.1.5
Summary: Creates a socket in a new process
Home-page: https://github.com/firejack6/multiprocessed-socket
Author: Jackson Frame
Author-email: frame_jackson@yahoo.com
Project-URL: Bug Tracker, https://github.com/firejack6/multiprocessed-socket/issues
Project-URL: repository, https://github.com/firejack6/multiprocessed-socket
Classifier: Programming Language :: Python :: 3
Classifier: License :: OSI Approved :: MIT License
Classifier: Operating System :: OS Independent
Requires-Python: >=3.6
License-File: LICENSE.txt
Requires-Dist: netifaces
Requires-Dist: socket
Requires-Dist: multiprocessing
Requires-Dist: threading
